{"events": [{"start_date": {"year": "1553", "month": "9", "day": "2"}, "media": {"thumbnail": "../../static/green.jpg"}, "text": {"headline": "2.9.1553, location: Hedelfingen", "text": "Briefwechsel zwischen Heinrich Bullinger und Petrus Venetscher"}}, {"start_date": {"year": "1555", "month": "9", "day": "2"}, "media": {"thumbnail": "../../static/green.jpg"}, "text": {"headline": "2.9.1555, location: Hedelfingen", "text": "Briefwechsel zwischen Heinrich Bullinger und Petrus Venetscher"}}, {"start_date": {"year": "1557", "month": "9", "day": "2"}, "media": {"thumbnail": "../../static/green.jpg"}, "text": {"headline": "2.9.1557, location: Hedelfingen", "text": "Briefwechsel zwischen Heinrich Bullinger und Petrus Venetscher"}}]}